AUTHORS.rst
CONTRIBUTING.rst
HISTORY.rst
LICENSE
MANIFEST.in
README.rst
setup.cfg
setup.py
docs/Makefile
docs/authors.rst
docs/conf.py
docs/contributing.rst
docs/history.rst
docs/index.rst
docs/installation.rst
docs/make.bat
docs/readme.rst
docs/usage.rst
pyphics/__init__.py
pyphics/cli.py
pyphics/pyphics.py
pyphics.egg-info/PKG-INFO
pyphics.egg-info/SOURCES.txt
pyphics.egg-info/dependency_links.txt
pyphics.egg-info/entry_points.txt
pyphics.egg-info/not-zip-safe
pyphics.egg-info/requires.txt
pyphics.egg-info/top_level.txt
tests/__init__.py
tests/test_pyphics.py