Metadata-Version: 1.1
Name: pyphics
Version: 0.1.0
Summary: Python graphics library based on D3js
Home-page: https://github.com/amitjha21/pyphics
Author: Amit Jha
Author-email: amit@amit-jha.com
License: MIT license
Keywords: pyphics
Platform: UNKNOWN
Classifier: Development Status :: 2 - Pre-Alpha
Classifier: Intended Audience :: Developers
Classifier: License :: OSI Approved :: MIT License
Classifier: Natural Language :: English
Classifier: Programming Language :: Python :: 2
Classifier: Programming Language :: Python :: 2.7
Classifier: Programming Language :: Python :: 3
Classifier: Programming Language :: Python :: 3.4
Classifier: Programming Language :: Python :: 3.5
Classifier: Programming Language :: Python :: 3.6
Classifier: Programming Language :: Python :: 3.7
